ezkl_gpu-16.1.0.dist-info/METADATA
ezkl_gpu-16.1.0.dist-info/WHEEL
ezkl.libs/libcuda-b1c54397.so.1
ezkl.libs/libcudart-c64a25f3.so.12
ezkl/__init__.py
ezkl/ezkl.abi3.so
ezkl_gpu-16.1.0.dist-info/RECORD
